{
    "simulation": {
        "simulationid": "tier_wideio_id2316_ai_cpu_trace",
        "simconfig": "../simconfig/example.json",
        "memspec": "../memspec/JEDEC_256Mb_WIDEIO-266_128bit.json",
        "addressmapping": "../addressmapping/am_wideio_4x256Mb_brc.json",
        "mcconfig": "../mcconfig/fr_fcfs_noref.json",
        "tracesetup": [
            {
                "type": "player",
                "clkMhz": 1000,
                "name": "/home/arifh/DRAMSys/experiments/traces/ai_cpu_trace.stl"
            }
        ]
    }
}